pyrestissimo/MSF_pb2.py
pyrestissimo/__init__.py
pyrestissimo/dbTable.npy
pyrestissimo/envTable.npy
pyrestissimo/note.py
pyrestissimo/prestissimo.py
pyrestissimo/prestissimo1.py
pyrestissimo/sampledb.py
pyrestissimo/utils.py
pyrestissimo-0.1.1.dist-info/METADATA
pyrestissimo-0.1.1.dist-info/WHEEL
pyrestissimo-0.1.1.dist-info/top_level.txt
pyrestissimo-0.1.1.dist-info/RECORD
